agithub/AppVeyor.py
agithub/DigitalOcean.py
agithub/Facebook.py
agithub/GitHub.py
agithub/Maven.py
agithub/OpenWeatherMap.py
agithub/SalesForce.py
agithub/__init__.py
agithub/agithub_test.py
agithub/base.py
agithub/test.py
agithub-2.2.2.dist-info/COPYING
agithub-2.2.2.dist-info/METADATA
agithub-2.2.2.dist-info/WHEEL
agithub-2.2.2.dist-info/top_level.txt
agithub-2.2.2.dist-info/RECORD
