Metadata-Version: 2.1
Name: agithub
Version: 2.2.2
Summary: A lightweight, transparent syntax for REST clients
Home-page: https://github.com/mozilla/agithub
Author: Jonathan Paugh
Author-email: jpaugh@gmx.us
License: MIT
Keywords: api,REST,GitHub,Facebook,SalesForce
Platform: UNKNOWN
Classifier: Development Status :: 5 - Production/Stable
Classifier: Environment :: Console
Classifier: Intended Audience :: Developers
Classifier: Operating System :: OS Independent
Classifier: Programming Language :: Python :: 2.6
Classifier: Programming Language :: Python :: 3
Classifier: Topic :: Utilities
